diagfig/__init__.py
diagfig/colour_config.py
diagfig/figure_diagnosis.py
diagfig/utils.py
diagfig/data/color_space.png
diagfig/data/example.png
diagfig/data/småliver.png
diagfig-0.2.1.dist-info/LICENSE
diagfig-0.2.1.dist-info/METADATA
diagfig-0.2.1.dist-info/WHEEL
diagfig-0.2.1.dist-info/top_level.txt
diagfig-0.2.1.dist-info/RECORD
