Metadata-Version: 2.1
Name: diagfig
Version: 0.2.1
Summary: Helpers to check if a figure is black and white and colourblind-friendly
Author-email: Vincent Pons <vincent.pons16@gmail.com>
License: MIT
Project-URL: homepage, https://github.com/vjtpons/diagfig
Keywords: colourblind,black_and_white,figure,scientific_publication
Classifier: Programming Language :: Python :: 3
Classifier: License :: OSI Approved :: MIT License
Classifier: Operating System :: OS Independent
Classifier: Development Status :: 1 - Planning
Classifier: Natural Language :: English
Classifier: Intended Audience :: Science/Research
Requires-Python: >=3.10
License-File: LICENSE
Requires-Dist: numpy
Requires-Dist: matplotlib
Requires-Dist: pillow
